{
  "$schema": "https://raw.githubusercontent.com/grafana/grafana/master/docs/sources/developers/plugins/plugin.schema.json",
  "type": "panel",
  "name": "my-grafana-plugin",
  "id": "id-my-grafana-plugin",
  "info": {
    "description": "",
    "author": {
      "name": "Shlokova",
      "url": ""
    },
    "keywords": [],
    "logos": {
      "small": "img/logo.svg",
      "large": "img/logo.svg"
    },

    "screenshots": [],
    "version": "1.0.0",
    "updated": "2022-05-15"
  },
  "dependencies": {
    "grafanaDependency": ">=7.0.0",
    "plugins": []
  }
}
